{
  "conflitti": [],
  "debolezza": "i18n:traits.mucose_barofile.debolezza",
  "famiglia_tipologia": "Tegumentario/Difensivo",
  "fattore_mantenimento_energetico": "i18n:traits.mucose_barofile.fattore_mantenimento_energetico",
  "id": "mucose_barofile",
  "label": "i18n:traits.mucose_barofile.label",
  "mutazione_indotta": "i18n:traits.mucose_barofile.mutazione_indotta",
  "requisiti_ambientali": [
    {
      "capacita_richieste": [],
      "condizioni": {
        "biome_class": "abisso_vulcanico"
      },
      "fonte": "env_to_traits",
      "meta": {
        "expansion": "coverage_q4_2025",
        "notes": "Mucose Barofile ottimizza le operazioni difensivo nelle condizioni di abisso vulcanico.",
        "tier": "T1"
      }
    }
  ],
  "sinergie": [
    "carapace_fase_variabile",
    "mimetismo_cromatico_passivo"
  ],
  "sinergie_pi": {
    "co_occorrenze": [],
    "combo_totale": 2,
    "forme": [],
    "tabelle_random": []
  },
  "slot": [],
  "slot_profile": {
    "complementare": "protezione",
    "core": "difensivo"
  },
  "spinta_selettiva": "i18n:traits.mucose_barofile.spinta_selettiva",
  "tier": "T1",
  "uso_funzione": "i18n:traits.mucose_barofile.uso_funzione",
  "usage_tags": [
    "tank"
  ],
  "completion_flags": {
    "has_biome": true,
    "has_species_link": false,
    "has_usage_tags": true,
    "has_data_origin": true
  },
  "biome_tags": [
    "abisso_vulcanico"
  ],
  "data_origin": "coverage_q4_2025"
}
