{"inkVersion":21,"root":[["^Comandante, squadra pronta per la missione.","\n","^Rapporto: bioma target con resistenze variabili.","\n","ev","str","^Assalto diretto","/str","/ev",{"*":"0.c-0","flg":20},"ev","str","^Ricognizione prima","/str","/ev",{"*":"0.c-1","flg":20},{"c-0":["\n","^Assalto confermato. Formazione serrata.","\n","#","^speaker:commander","/#","#","^mood:determined","/#",{"->":"debrief"},{"->":"0.g-0"},{"#f":5}],"c-1":["\n","^Ricognizione avviata. Scanner attivi, difensiva.","\n","#","^speaker:commander","/#","#","^mood:cautious","/#",{"->":"debrief"},{"->":"0.g-0"},{"#f":5}],"g-0":["done",null]}],"done",{"debrief":["^Missione completata. Analisi performance in corso.","\n","#","^speaker:analyst","/#","^Fine rapporto.","\n","end",null]}],"listDefs":{}}