{
  "completion_flags": {
    "has_biome": true,
    "has_data_origin": true,
    "has_species_link": true,
    "has_usage_tags": true
  },
  "conflitti": [],
  "data_origin": "coverage_q4_2025",
  "debolezza": "Suscettibile a disturbi elettromagnetici e saturazione sensoriale.",
  "famiglia_tipologia": "Sensoriale/Analitico",
  "fattore_mantenimento_energetico": "Basso (Passivo)",
  "id": "ali_fulminee",
  "label": "Ali Fulminee",
  "mutazione_indotta": "innesta recettori stratificati che filtrano impulsi elettromagnetici e feromoni.",
  "requisiti_ambientali": [
    {
      "capacita_richieste": [],
      "condizioni": {
        "biome_class": "stratosfera_tempestosa"
      },
      "fonte": "env_to_traits",
      "meta": {
        "expansion": "coverage_q4_2025",
        "notes": "Ali Fulminee ottimizza le operazioni sensoriale nelle condizioni di stratosfera tempestosa.",
        "tier": "T1"
      }
    }
  ],
  "sinergie": [
    "focus_frazionato",
    "sinapsi_coraline_polifoniche"
  ],
  "sinergie_pi": {
    "co_occorrenze": [],
    "combo_totale": 2,
    "forme": [],
    "tabelle_random": []
  },
  "slot": [],
  "slot_profile": {
    "complementare": "analitico",
    "core": "sensoriale"
  },
  "species_affinity": [
    {
      "roles": [
        "optional"
      ],
      "species_id": "stratosfera-tempestosa-trait-keeper",
      "weight": 1
    }
  ],
  "spinta_selettiva": "Mantenere consapevolezza costante in biomi ad alta entropia percettiva.",
  "tier": "T1",
  "usage_tags": [
    "scout",
    "support"
  ],
  "uso_funzione": "Amplifica percezioni multi-spettro e fornisce orientamento tattile immediato."
}
