[
  {
    "alertId": "risk-high:evt-01",
    "status": "raised",
    "missionId": "EVT-01",
    "missionTag": "evt-01",
    "turn": 5,
    "weightedIndex": 0.62,
    "timeLowHpTurns": 2,
    "timestamp": "2025-02-27T14:15:04Z",
    "ackCount": 0,
    "ackRecipients": []
  },
  {
    "alertId": "risk-high:evt-01",
    "status": "acknowledged",
    "missionId": "EVT-01",
    "missionTag": "evt-01",
    "turn": 6,
    "weightedIndex": 0.61,
    "timeLowHpTurns": 2,
    "timestamp": "2025-02-27T14:15:28Z",
    "ackRecipient": "HUD",
    "ackRecipients": ["HUD"],
    "ackCount": 1,
    "lastAckTimestamp": "2025-02-27T14:15:28Z"
  },
  {
    "alertId": "risk-high:evt-01",
    "status": "cleared",
    "missionId": "EVT-01",
    "missionTag": "evt-01",
    "turn": 7,
    "weightedIndex": 0.57,
    "timeLowHpTurns": 1,
    "timestamp": "2025-02-27T14:16:02Z",
    "ackRecipients": ["HUD"],
    "ackCount": 1,
    "lastAckTimestamp": "2025-02-27T14:15:28Z"
  },
  {
    "alertId": "risk-high:evt-01",
    "status": "filtered",
    "missionId": "EVT-01",
    "missionTag": "evt-01",
    "turn": 4,
    "weightedIndex": 0.58,
    "timeLowHpTurns": 1,
    "timestamp": "2025-02-27T14:14:41Z",
    "filterName": "vfxSettlingGuard",
    "filterCount": 1
  }
]
